AUTHORS
ChangeLog
LICENSE
README.rst
requirements.txt
setup.cfg
setup.py
test-requirements.txt
tox.ini
schemadisplay_sphinx/__init__.py
schemadisplay_sphinx.egg-info/PKG-INFO
schemadisplay_sphinx.egg-info/SOURCES.txt
schemadisplay_sphinx.egg-info/dependency_links.txt
schemadisplay_sphinx.egg-info/not-zip-safe
schemadisplay_sphinx.egg-info/pbr.json
schemadisplay_sphinx.egg-info/requires.txt
schemadisplay_sphinx.egg-info/top_level.txt