Metadata-Version: 1.1
Name: schemadisplay-sphinx
Version: 0.0.1
Summary: Sphinx Extension for Schema generation
Home-page: https://github.com/electrocucaracha/schemadisplay_sphinx
Author: Victor Morales
Author-email: electrocucaracha@gmail.com
License: UNKNOWN
Platform: UNKNOWN
Classifier: Intended Audience :: Information Technology
Classifier: Intended Audience :: System Administrators
Classifier: License :: OSI Approved :: Apache Software License
Classifier: Operating System :: POSIX :: Linux
Classifier: Programming Language :: Python
Classifier: Programming Language :: Python :: 2
Classifier: Programming Language :: Python :: 2.7
Classifier: Topic :: Documentation
